setup.py
zvbot.py
zvbot.egg-info/PKG-INFO
zvbot.egg-info/SOURCES.txt
zvbot.egg-info/dependency_links.txt
zvbot.egg-info/entry_points.txt
zvbot.egg-info/not-zip-safe
zvbot.egg-info/requires.txt
zvbot.egg-info/top_level.txt